ez_mcp_toolbox/__init__.py
ez_mcp_toolbox/chatbot.py
ez_mcp_toolbox/evaluator.py
ez_mcp_toolbox/mcp_utils.py
ez_mcp_toolbox/optimizer.py
ez_mcp_toolbox/server.py
ez_mcp_toolbox/session.py
ez_mcp_toolbox/utils.py
ez_mcp_toolbox-1.5.0.dist-info/licenses/LICENSE
ez_mcp_toolbox-1.5.0.dist-info/METADATA
ez_mcp_toolbox-1.5.0.dist-info/WHEEL
ez_mcp_toolbox-1.5.0.dist-info/entry_points.txt
ez_mcp_toolbox-1.5.0.dist-info/top_level.txt
ez_mcp_toolbox-1.5.0.dist-info/RECORD
