Metadata-Version: 2.4
Name: ez-mcp-toolbox
Version: 1.5.0
Summary: Utilities for creating and debugging MCP tools
Author-email: Opik Team <support@comet.com>
Maintainer-email: Opik Team <support@comet.com>
License:                                  Apache License
Project-URL: Homepage, https://github.com/comet-ml/ez-mcp-toolbox
Project-URL: Repository, https://github.com/comet-ml/ez-mcp-toolbox
Project-URL: Documentation, https://github.com/comet-ml/ez-mcp-toolbox#readme
Project-URL: Bug Tracker, https://github.com/comet-ml/ez-mcp-toolbox/issues
Keywords: opik,mcp,model-context-protocol,llm,observability,debugging
Classifier: Development Status :: 4 - Beta
Classifier: Intended Audience :: Developers
Classifier: Intended Audience :: Science/Research
Classifier: License :: OSI Approved :: Apache Software License
Classifier: Operating System :: OS Independent
Classifier: Programming Language :: Python :: 3
Classifier: Programming Language :: Python :: 3.9
Classifier: Programming Language :: Python :: 3.10
Classifier: Programming Language :: Python :: 3.11
Classifier: Programming Language :: Python :: 3.12
Classifier: Topic :: Scientific/Engineering :: Artificial Intelligence
Classifier: Topic :: Software Development :: Libraries :: Python Modules
Requires-Python: >=3.9
License-File: LICENSE
Requires-Dist: fastapi>=0.100.0
Requires-Dist: httpx>=0.25.0
Requires-Dist: litellm>=1.0.0
Requires-Dist: mcp>=1.0.0
Requires-Dist: pydantic>=2.0.0
Requires-Dist: python-dotenv>=1.0.0
Requires-Dist: rich>=13.0.0
Requires-Dist: typing-extensions>=4.0.0
Requires-Dist: uvicorn[standard]>=0.20.0
Requires-Dist: prompt-toolkit>=3.0.0
Requires-Dist: nest-asyncio>=1.5.0
Requires-Dist: pillow>=9.0.0
Requires-Dist: opik>=1.8.97
Requires-Dist: opik_optimizer>=2.2.1
Requires-Dist: matplotlib>=3.5.0
Provides-Extra: dev
Requires-Dist: pytest>=7.0.0; extra == "dev"
Requires-Dist: pytest-asyncio>=0.21.0; extra == "dev"
Requires-Dist: black>=23.0.0; extra == "dev"
Requires-Dist: isort>=5.12.0; extra == "dev"
Requires-Dist: flake8>=6.0.0; extra == "dev"
Requires-Dist: mypy>=1.0.0; extra == "dev"
Provides-Extra: test
Requires-Dist: pytest>=7.0.0; extra == "test"
Requires-Dist: pytest-asyncio>=0.21.0; extra == "test"
Dynamic: license-file
